hashcons/__init__.py
hashcons/instance_store.py
hashcons/py.typed
hashcons-0.1.0.dist-info/LICENSE
hashcons-0.1.0.dist-info/METADATA
hashcons-0.1.0.dist-info/WHEEL
hashcons-0.1.0.dist-info/top_level.txt
hashcons-0.1.0.dist-info/RECORD
