Metadata-Version: 2.1
Name: hashcons
Version: 0.1.0
Summary: Hash consing for flyweight instance management.
Author: Hashberg
Project-URL: Documentation, https://hashcons.readthedocs.io
Project-URL: Repository, https://github.com/hashberg-io/hashcons
Project-URL: Issues, https://github.com/hashberg-io/hashcons/issues
Classifier: Programming Language :: Python :: 3
Classifier: Operating System :: OS Independent
Classifier: Development Status :: 4 - Beta
Classifier: Programming Language :: Python :: 3.12
Classifier: Programming Language :: Python :: 3.11
Classifier: Programming Language :: Python :: 3.10
Classifier: Programming Language :: Python :: 3.9
Classifier: Natural Language :: English
Classifier: Typing :: Typed
Requires-Python: >=3.9
License-File: LICENSE
Requires-Dist: typing-extensions>=4.12.2
